pypac4http2/__init__.py
pypac4http2/cli.py
pypac4http2/http_pac.py
pypac4http2/utils.py
pypac4http2-0.0.7.dist-info/licenses/LICENSE
pypac4http2-0.0.7.dist-info/METADATA
pypac4http2-0.0.7.dist-info/WHEEL
pypac4http2-0.0.7.dist-info/entry_points.txt
pypac4http2-0.0.7.dist-info/top_level.txt
pypac4http2-0.0.7.dist-info/RECORD
