Metadata-Version: 2.4
Name: pypac4http2
Version: 0.0.7
Summary: Python package which builds on pypac to add pac file support for httplib2 Http
Author-email: Mike Moore <z_z_zebra@yahoo.com>
License-Expression: Apache-2.0
Classifier: Development Status :: 4 - Beta
Classifier: Environment :: Web Environment
Classifier: Intended Audience :: Developers
Classifier: Operating System :: OS Independent
Classifier: Programming Language :: Python :: 3
Classifier: Programming Language :: Python :: 3.10
Classifier: Programming Language :: Python :: 3.11
Classifier: Programming Language :: Python :: 3.12
Classifier: Programming Language :: Python :: 3.13
Classifier: Programming Language :: Python :: 3.14
Classifier: Topic :: Internet
Classifier: Topic :: Internet :: WWW/HTTP
Classifier: Topic :: Software Development :: Libraries :: Python Modules
Requires-Python: >=3.10
License-File: LICENSE
Requires-Dist: httplib2>=0.22.0
Requires-Dist: pypac>=0.17.0
Requires-Dist: PySocks>=1.7.1
Provides-Extra: dev
Requires-Dist: pytest>=7.0; extra == "dev"
Requires-Dist: pytest-cov>=4.0; extra == "dev"
Requires-Dist: tox>=4.0; extra == "dev"
Requires-Dist: black>=23.0; extra == "dev"
Dynamic: license-file
